Gauss/MetGauss.py
Gauss/__init__.py
Metodo_GaussJordan-0.1.dist-info/LICENSE
Metodo_GaussJordan-0.1.dist-info/METADATA
Metodo_GaussJordan-0.1.dist-info/WHEEL
Metodo_GaussJordan-0.1.dist-info/top_level.txt
Metodo_GaussJordan-0.1.dist-info/RECORD
